README.md
setup.py
bin/dialogpt2-gen
bin/dialogpt2-train
dialogpt2/__init__.py
dialogpt2/model.py
dialogpt2.egg-info/PKG-INFO
dialogpt2.egg-info/SOURCES.txt
dialogpt2.egg-info/dependency_links.txt
dialogpt2.egg-info/top_level.txt