Metadata-Version: 2.1
Name: dialogpt2
Version: 1.0
Summary: DialoGTP2 train/gen
Home-page: https://github.com/dialogpt2
Author: ysig
Author-email: yiannis@echochamber.be
License: Apache 2.0 Software license
Platform: UNKNOWN
Classifier: Development Status :: 5 - Production/Stable
Classifier: Intended Audience :: Developers
Classifier: Intended Audience :: Education
Classifier: Intended Audience :: Science/Research
Classifier: License :: OSI Approved :: Apache Software License
Classifier: Operating System :: OS Independent
Classifier: Programming Language :: Python :: 3
Classifier: Programming Language :: Python :: 3.6
Classifier: Programming Language :: Python :: 3.7
Classifier: Topic :: Scientific/Engineering :: Artificial Intelligence
Requires-Python: >=3.5
